{
  "locked": false,
  "version": -9998,
  "projectFileDependencyGroups": {
    "": [
      "Microsoft.Framework.Runtime >= 1.0.0-*",
      "Microsoft.Framework.Runtime.Roslyn >= 1.0.0-*"
    ],
    "DNX,Version=v4.5.1": [],
    "DNXCore,Version=v5.0": [
      "System.IO >= 4.0.10-*",
      "System.Collections >= 4.0.10-*",
      "System.Runtime >= 4.0.20-*",
      "System.Runtime.Extensions >= 4.0.10-*",
      "System.Reflection >= 4.0.10-*",
      "System.Reflection.Emit >= 4.0.0-*",
      "System.Reflection.Emit.Lightweight >= 4.0.0-*",
      "System.Reflection.Emit.ILGeneration >= 4.0.0-*",
      "System.Reflection.TypeExtensions >= 4.0.0-*"
    ]
  },
  "libraries": {
    "Microsoft.CodeAnalysis.Analyzers/1.0.0-rc2-20150325-03": {
      "serviceable": false,
      "sha": "zazOEKMszvdWD/TjtjWhpO1EZt3vYnjJiLeRd3SmXbfYrbQxoYknncH56+ZUt5/g0ZbE3jBlo87n+tW6ZytVJQ==",
      "frameworks": {
        "DNX,Version=v4.5.1": {
          "dependencies": {},
          "frameworkAssemblies": [
            "System"
          ],
          "runtimeAssemblies": [],
          "compileAssemblies": []
        },
        "DNXCore,Version=v5.0": {
          "dependencies": {},
          "frameworkAssemblies": [],
          "runtimeAssemblies": [],
          "compileAssemblies": []
        }
      },
      "files": [
        "Microsoft.CodeAnalysis.Analyzers.1.0.0-rc2-20150325-03.nupkg",
        "Microsoft.CodeAnalysis.Analyzers.1.0.0-rc2-20150325-03.nupkg.sha512",
        "Microsoft.CodeAnalysis.Analyzers.nuspec",
        "ThirdPartyNotices.rtf",
        "tools/install.ps1",
        "tools/uninstall.ps1",
        "tools/analyzers/C#/Microsoft.CodeAnalysis.Analyzers.dll",
        "tools/analyzers/C#/Microsoft.CodeAnalysis.CSharp.Analyzers.dll",
        "tools/analyzers/VB.NET/Microsoft.CodeAnalysis.Analyzers.dll",
        "tools/analyzers/VB.NET/Microsoft.CodeAnalysis.VisualBasic.Analyzers.dll"
      ]
    },
    "Microsoft.CodeAnalysis.Common/1.0.0-rc2-20150325-03": {
      "serviceable": false,
      "sha": "eG/VBVPsOHXyWaxCdoirSfoYdxC5z6LrYijdVAnnV8NCmiO21nN+Adzqdihh7PAkKBRLNBG2k4A06RhtxrI8mQ==",
      "frameworks": {
        "DNX,Version=v4.5.1": {
          "dependencies": {
            "System.Collections.Immutable": "[1.1.33-beta]",
            "System.Reflection.Metadata": "[1.0.18-beta]",
            "Microsoft.CodeAnalysis.Analyzers": "[1.0.0-rc2-20150325-03]"
          },
          "frameworkAssemblies": [],
          "runtimeAssemblies": [
            "lib/net45/Microsoft.CodeAnalysis.Desktop.dll",
            "lib/net45/Microsoft.CodeAnalysis.dll"
          ],
          "compileAssemblies": [
            "lib/net45/Microsoft.CodeAnalysis.Desktop.dll",
            "lib/net45/Microsoft.CodeAnalysis.dll"
          ]
        },
        "DNXCore,Version=v5.0": {
          "dependencies": {
            "System.Collections.Immutable": "[1.1.33-beta]",
            "System.Reflection.Metadata": "[1.0.18-beta]",
            "Microsoft.CodeAnalysis.Analyzers": "[1.0.0-rc2-20150325-03]"
          },
          "frameworkAssemblies": [],
          "runtimeAssemblies": [
            "lib/portable-net45+win8/Microsoft.CodeAnalysis.dll"
          ],
          "compileAssemblies": [
            "lib/portable-net45+win8/Microsoft.CodeAnalysis.dll"
          ]
        }
      },
      "files": [
        "Microsoft.CodeAnalysis.Common.1.0.0-rc2-20150325-03.nupkg",
        "Microsoft.CodeAnalysis.Common.1.0.0-rc2-20150325-03.nupkg.sha512",
        "Microsoft.CodeAnalysis.Common.nuspec",
        "ThirdPartyNotices.rtf",
        "lib/net45/Microsoft.CodeAnalysis.Desktop.dll",
        "lib/net45/Microsoft.CodeAnalysis.Desktop.xml",
        "lib/net45/Microsoft.CodeAnalysis.dll",
        "lib/net45/Microsoft.CodeAnalysis.xml",
        "lib/portable-net45+win8/Microsoft.CodeAnalysis.dll",
        "lib/portable-net45+win8/Microsoft.CodeAnalysis.xml"
      ]
    },
    "Microsoft.CodeAnalysis.CSharp/1.0.0-rc2-20150325-03": {
      "serviceable": false,
      "sha": "qLkypvKmbmrUY4VlZ7T2VhEjDy8YqTSptEnjB5GF1l0jM5bcPJG0lCzQlOtRGhySm+OW1ldh8CKUHAxaNAoRLw==",
      "frameworks": {
        "DNX,Version=v4.5.1": {
          "dependencies": {
            "Microsoft.CodeAnalysis.Common": "[1.0.0-rc2-20150325-03]"
          },
          "frameworkAssemblies": [],
          "runtimeAssemblies": [
            "lib/net45/Microsoft.CodeAnalysis.CSharp.Desktop.dll",
            "lib/net45/Microsoft.CodeAnalysis.CSharp.dll"
          ],
          "compileAssemblies": [
            "lib/net45/Microsoft.CodeAnalysis.CSharp.Desktop.dll",
            "lib/net45/Microsoft.CodeAnalysis.CSharp.dll"
          ]
        },
        "DNXCore,Version=v5.0": {
          "dependencies": {
            "Microsoft.CodeAnalysis.Common": "[1.0.0-rc2-20150325-03]"
          },
          "frameworkAssemblies": [],
          "runtimeAssemblies": [
            "lib/portable-net45+win8/Microsoft.CodeAnalysis.CSharp.dll"
          ],
          "compileAssemblies": [
            "lib/portable-net45+win8/Microsoft.CodeAnalysis.CSharp.dll"
          ]
        }
      },
      "files": [
        "Microsoft.CodeAnalysis.CSharp.1.0.0-rc2-20150325-03.nupkg",
        "Microsoft.CodeAnalysis.CSharp.1.0.0-rc2-20150325-03.nupkg.sha512",
        "Microsoft.CodeAnalysis.CSharp.nuspec",
        "ThirdPartyNotices.rtf",
        "lib/net45/Microsoft.CodeAnalysis.CSharp.Desktop.dll",
        "lib/net45/Microsoft.CodeAnalysis.CSharp.Desktop.xml",
        "lib/net45/Microsoft.CodeAnalysis.CSharp.dll",
        "lib/net45/Microsoft.CodeAnalysis.CSharp.xml",
        "lib/portable-net45+win8/Microsoft.CodeAnalysis.CSharp.dll",
        "lib/portable-net45+win8/Microsoft.CodeAnalysis.CSharp.xml"
      ]
    },
    "Microsoft.Framework.Runtime/1.0.0-beta5-11380": {
      "serviceable": false,
      "sha": "eGr8ieI/miVsT49vVvauodZYM9AhmHI3OWk4RugEtAs6+gDSI0O0AWY3p1eF1aKoTKp7y0sAtoqQXNKH0FCgkA==",
      "frameworks": {
        "DNX,Version=v4.5.1": {
          "dependencies": {
            "System.Reflection.Metadata": "1.0.18-beta",
            "Microsoft.CodeAnalysis.CSharp": "1.0.0-rc2-20150325-03",
            "Microsoft.Framework.Runtime.Roslyn.Interfaces": "1.0.0-beta5-11380",
            "Microsoft.Framework.Runtime.Loader": "1.0.0-beta5-11380",
            "Microsoft.Framework.Runtime.Interfaces": "1.0.0-beta5-11380",
            "Newtonsoft.Json": "6.0.6"
          },
          "frameworkAssemblies": [
            "System.Collections",
            "System.Text.Encoding",
            "System.Threading.Tasks",
            "System.IO",
            "System.IO.Compression",
            "System.IO.Compression.FileSystem",
            "System.Runtime",
            "System.Xml",
            "System.Xml.Linq",
            "mscorlib",
            "System",
            "System.Core",
            "Microsoft.CSharp"
          ],
          "runtimeAssemblies": [
            "lib/dnx451/Microsoft.Framework.Runtime.dll"
          ],
          "compileAssemblies": [
            "lib/dnx451/Microsoft.Framework.Runtime.dll"
          ]
        },
        "DNXCore,Version=v5.0": {
          "dependencies": {
            "System.Reflection.Metadata": "1.0.18-beta",
            "Microsoft.CodeAnalysis.CSharp": "1.0.0-rc2-20150325-03",
            "Microsoft.Framework.Runtime.Roslyn.Interfaces": "1.0.0-beta5-11380",
            "Microsoft.Framework.Runtime.Loader": "1.0.0-beta5-11380",
            "Microsoft.Framework.Runtime.Interfaces": "1.0.0-beta5-11380",
            "Newtonsoft.Json": "6.0.6",
            "System.Collections.Concurrent": "4.0.10-beta-22725",
            "System.Diagnostics.Tools": "4.0.0-beta-22725",
            "System.Dynamic.Runtime": "4.0.10-beta-22725",
            "System.Globalization": "4.0.10-beta-22725",
            "System.IO.Compression": "4.0.0-beta-22725",
            "System.IO.FileSystem.Watcher": "4.0.0-beta-22725",
            "System.Linq": "4.0.0-beta-22725",
            "System.Net.Sockets": "4.0.0-beta-22725",
            "System.Reflection.Extensions": "4.0.0-beta-22725",
            "System.Resources.ResourceManager": "4.0.0-beta-22725",
            "System.Text.Encoding": "4.0.10-beta-22725",
            "System.Text.RegularExpressions": "4.0.10-beta-22725",
            "System.Threading.Timer": "4.0.0-beta-22725",
            "System.Threading.Tasks": "4.0.10-beta-22725",
            "System.Threading.Thread": "4.0.0-beta-22725",
            "System.Threading.ThreadPool": "4.0.10-beta-22725",
            "System.Xml.ReaderWriter": "4.0.10-beta-22725",
            "System.Xml.XDocument": "4.0.10-beta-22725",
            "System.Xml.XmlSerializer": "4.0.10-beta-22725"
          },
          "frameworkAssemblies": [],
          "runtimeAssemblies": [
            "lib/dnxcore50/Microsoft.Framework.Runtime.dll"
          ],
          "compileAssemblies": [
            "lib/dnxcore50/Microsoft.Framework.Runtime.dll"
          ]
        }
      },
      "files": [
        "Microsoft.Framework.Runtime.1.0.0-beta5-11380.nupkg",
        "Microsoft.Framework.Runtime.1.0.0-beta5-11380.nupkg.sha512",
        "Microsoft.Framework.Runtime.nuspec",
        "lib/dnx451/Microsoft.Framework.Runtime.dll",
        "lib/dnx451/Microsoft.Framework.Runtime.xml",
        "lib/dnxcore50/Microsoft.Framework.Runtime.dll",
        "lib/dnxcore50/Microsoft.Framework.Runtime.xml"
      ]
    },
    "Microsoft.Framework.Runtime.Interfaces/1.0.0-beta5-11380": {
      "serviceable": false,
      "sha": "ajgmfYqqSFJKWcxAs3ymgW0xfXikVovopojGliVUHMjCwVvec/rM6dZtF/qzgEZ+toP8T+UAKBkkFq7LGkAlwQ==",
      "frameworks": {
        "DNX,Version=v4.5.1": {
          "dependencies": {},
          "frameworkAssemblies": [
            "mscorlib",
            "System",
            "System.Core",
            "Microsoft.CSharp"
          ],
          "runtimeAssemblies": [
            "lib/dnx451/Microsoft.Framework.Runtime.Interfaces.dll"
          ],
          "compileAssemblies": [
            "lib/dnx451/Microsoft.Framework.Runtime.Interfaces.dll"
          ]
        },
        "DNXCore,Version=v5.0": {
          "dependencies": {
            "System.IO": "4.0.10-beta-22725",
            "System.Reflection": "4.0.10-beta-22725",
            "System.Runtime": "4.0.20-beta-22725",
            "System.Runtime.Extensions": "4.0.10-beta-22725",
            "System.Threading.Tasks": "4.0.10-beta-22725",
            "System.ComponentModel": "4.0.0-beta-22725"
          },
          "frameworkAssemblies": [],
          "runtimeAssemblies": [
            "lib/dnxcore50/Microsoft.Framework.Runtime.Interfaces.dll"
          ],
          "compileAssemblies": [
            "lib/dnxcore50/Microsoft.Framework.Runtime.Interfaces.dll"
          ]
        }
      },
      "files": [
        "Microsoft.Framework.Runtime.Interfaces.1.0.0-beta5-11380.nupkg",
        "Microsoft.Framework.Runtime.Interfaces.1.0.0-beta5-11380.nupkg.sha512",
        "Microsoft.Framework.Runtime.Interfaces.nuspec",
        "lib/dnx451/Microsoft.Framework.Runtime.Interfaces.dll",
        "lib/dnx451/Microsoft.Framework.Runtime.Interfaces.xml",
        "lib/dnxcore50/Microsoft.Framework.Runtime.Interfaces.dll",
        "lib/dnxcore50/Microsoft.Framework.Runtime.Interfaces.xml"
      ]
    },
    "Microsoft.Framework.Runtime.Loader/1.0.0-beta5-11380": {
      "serviceable": false,
      "sha": "jsMccfDumt5Pdew03pXrlXcueXUWJdDVAx4SBG9HKHgG4mMuNnd3yj0i6N3ME7hdyYMdr5FxYGDWKPOihfQaFA==",
      "frameworks": {
        "DNX,Version=v4.5.1": {
          "dependencies": {
            "Microsoft.Framework.Runtime.Interfaces": "1.0.0-beta5-11380"
          },
          "frameworkAssemblies": [
            "mscorlib",
            "System",
            "System.Core",
            "Microsoft.CSharp"
          ],
          "runtimeAssemblies": [
            "lib/dnx451/Microsoft.Framework.Runtime.Loader.dll"
          ],
          "compileAssemblies": [
            "lib/dnx451/Microsoft.Framework.Runtime.Loader.dll"
          ]
        },
        "DNXCore,Version=v5.0": {
          "dependencies": {
            "Microsoft.Framework.Runtime.Interfaces": "1.0.0-beta5-11380",
            "System.Collections": "4.0.10-beta-22725",
            "System.Collections.Concurrent": "4.0.10-beta-22725",
            "System.Runtime.Loader": "4.0.0-beta-22725",
            "System.IO.FileSystem": "4.0.0-beta-22725",
            "System.AppContext": "4.0.0-beta-22725",
            "System.Threading": "4.0.10-beta-22725"
          },
          "frameworkAssemblies": [],
          "runtimeAssemblies": [
            "lib/dnxcore50/Microsoft.Framework.Runtime.Loader.dll"
          ],
          "compileAssemblies": [
            "lib/dnxcore50/Microsoft.Framework.Runtime.Loader.dll"
          ]
        }
      },
      "files": [
        "Microsoft.Framework.Runtime.Loader.1.0.0-beta5-11380.nupkg",
        "Microsoft.Framework.Runtime.Loader.1.0.0-beta5-11380.nupkg.sha512",
        "Microsoft.Framework.Runtime.Loader.nuspec",
        "lib/dnx451/Microsoft.Framework.Runtime.Loader.dll",
        "lib/dnx451/Microsoft.Framework.Runtime.Loader.xml",
        "lib/dnxcore50/Microsoft.Framework.Runtime.Loader.dll",
        "lib/dnxcore50/Microsoft.Framework.Runtime.Loader.xml"
      ]
    },
    "Microsoft.Framework.Runtime.Roslyn/1.0.0-beta5-11380": {
      "serviceable": false,
      "sha": "RhtlUuiyCFAuoS8o/OpvgtXmaKEmKZR3496Cbj9YBZ8MAEqXTO4kKgVemIxO7M/tdEOouTJqnZvxwEgSXJVICA==",
      "frameworks": {
        "DNX,Version=v4.5.1": {
          "dependencies": {
            "Microsoft.Framework.Runtime": "1.0.0-beta5-11380",
            "Microsoft.Framework.Runtime.Interfaces": "1.0.0-beta5-11380",
            "Microsoft.Framework.Runtime.Roslyn.Interfaces": "1.0.0-beta5-11380"
          },
          "frameworkAssemblies": [
            "System.IO",
            "System.Xml",
            "System.Xml.Linq",
            "System.Threading.Tasks",
            "System.Text.Encoding",
            "mscorlib",
            "System",
            "System.Core",
            "Microsoft.CSharp"
          ],
          "runtimeAssemblies": [
            "lib/dnx451/Microsoft.Framework.Runtime.Roslyn.dll"
          ],
          "compileAssemblies": [
            "lib/dnx451/Microsoft.Framework.Runtime.Roslyn.dll"
          ]
        },
        "DNXCore,Version=v5.0": {
          "dependencies": {
            "Microsoft.Framework.Runtime": "1.0.0-beta5-11380",
            "Microsoft.Framework.Runtime.Interfaces": "1.0.0-beta5-11380",
            "Microsoft.Framework.Runtime.Roslyn.Interfaces": "1.0.0-beta5-11380",
            "System.Collections.Concurrent": "4.0.10-beta-22725",
            "System.Resources.ResourceWriter": "4.0.0-beta-22725",
            "System.Runtime.InteropServices": "4.0.20-beta-22725"
          },
          "frameworkAssemblies": [],
          "runtimeAssemblies": [
            "lib/dnxcore50/Microsoft.Framework.Runtime.Roslyn.dll"
          ],
          "compileAssemblies": [
            "lib/dnxcore50/Microsoft.Framework.Runtime.Roslyn.dll"
          ]
        }
      },
      "files": [
        "Microsoft.Framework.Runtime.Roslyn.1.0.0-beta5-11380.nupkg",
        "Microsoft.Framework.Runtime.Roslyn.1.0.0-beta5-11380.nupkg.sha512",
        "Microsoft.Framework.Runtime.Roslyn.nuspec",
        "lib/dnx451/Microsoft.Framework.Runtime.Roslyn.dll",
        "lib/dnx451/Microsoft.Framework.Runtime.Roslyn.xml",
        "lib/dnxcore50/Microsoft.Framework.Runtime.Roslyn.dll",
        "lib/dnxcore50/Microsoft.Framework.Runtime.Roslyn.xml"
      ]
    },
    "Microsoft.Framework.Runtime.Roslyn.Interfaces/1.0.0-beta5-11380": {
      "serviceable": false,
      "sha": "lGuJdBYmlLsyF/59nZP/IaX1vkjkQ6Np9FZBMK11O/zZs02yAuPX0zNzswRZgYCwZhpcwo/O4yZfUHB3ZfdKvg==",
      "frameworks": {
        "DNX,Version=v4.5.1": {
          "dependencies": {
            "Microsoft.Framework.Runtime.Interfaces": "1.0.0-beta5-11380",
            "Microsoft.CodeAnalysis.CSharp": "1.0.0-rc2-20150325-03"
          },
          "frameworkAssemblies": [
            "mscorlib",
            "System",
            "System.Core",
            "Microsoft.CSharp"
          ],
          "runtimeAssemblies": [
            "lib/dnx451/Microsoft.Framework.Runtime.Roslyn.Interfaces.dll"
          ],
          "compileAssemblies": [
            "lib/dnx451/Microsoft.Framework.Runtime.Roslyn.Interfaces.dll"
          ]
        },
        "DNXCore,Version=v5.0": {
          "dependencies": {
            "Microsoft.Framework.Runtime.Interfaces": "1.0.0-beta5-11380",
            "Microsoft.CodeAnalysis.CSharp": "1.0.0-rc2-20150325-03",
            "System.Runtime": "4.0.20-beta-22725"
          },
          "frameworkAssemblies": [],
          "runtimeAssemblies": [
            "lib/dnxcore50/Microsoft.Framework.Runtime.Roslyn.Interfaces.dll"
          ],
          "compileAssemblies": [
            "lib/dnxcore50/Microsoft.Framework.Runtime.Roslyn.Interfaces.dll"
          ]
        }
      },
      "files": [
        "Microsoft.Framework.Runtime.Roslyn.Interfaces.1.0.0-beta5-11380.nupkg",
        "Microsoft.Framework.Runtime.Roslyn.Interfaces.1.0.0-beta5-11380.nupkg.sha512",
        "Microsoft.Framework.Runtime.Roslyn.Interfaces.nuspec",
        "lib/dnx451/Microsoft.Framework.Runtime.Roslyn.Interfaces.dll",
        "lib/dnx451/Microsoft.Framework.Runtime.Roslyn.Interfaces.xml",
        "lib/dnxcore50/Microsoft.Framework.Runtime.Roslyn.Interfaces.dll",
        "lib/dnxcore50/Microsoft.Framework.Runtime.Roslyn.Interfaces.xml"
      ]
    },
    "Newtonsoft.Json/6.0.6": {
      "serviceable": false,
      "sha": "w26uZNyCG5VeoKiEOJ4+9/o8koSofLKwHl7WLreIcp0U6r57L7WiRXmjp8MTKFw6dYNZ9AE0lw69WYbIhUsU9Q==",
      "frameworks": {
        "DNX,Version=v4.5.1": {
          "dependencies": {},
          "frameworkAssemblies": [],
          "runtimeAssemblies": [
            "lib/net45/Newtonsoft.Json.dll"
          ],
          "compileAssemblies": [
            "lib/net45/Newtonsoft.Json.dll"
          ]
        },
        "DNXCore,Version=v5.0": {
          "dependencies": {},
          "frameworkAssemblies": [],
          "runtimeAssemblies": [
            "lib/portable-net45+wp80+win8+wpa81+aspnetcore50/Newtonsoft.Json.dll"
          ],
          "compileAssemblies": [
            "lib/portable-net45+wp80+win8+wpa81+aspnetcore50/Newtonsoft.Json.dll"
          ]
        }
      },
      "files": [
        "Newtonsoft.Json.6.0.6.nupkg",
        "Newtonsoft.Json.6.0.6.nupkg.sha512",
        "Newtonsoft.Json.nuspec",
        "lib/net20/Newtonsoft.Json.dll",
        "lib/net20/Newtonsoft.Json.xml",
        "lib/net35/Newtonsoft.Json.dll",
        "lib/net35/Newtonsoft.Json.xml",
        "lib/net40/Newtonsoft.Json.dll",
        "lib/net40/Newtonsoft.Json.xml",
        "lib/net45/Newtonsoft.Json.dll",
        "lib/net45/Newtonsoft.Json.xml",
        "lib/netcore45/Newtonsoft.Json.dll",
        "lib/netcore45/Newtonsoft.Json.xml",
        "lib/portable-net40+sl5+wp80+win8+wpa81/Newtonsoft.Json.dll",
        "lib/portable-net40+sl5+wp80+win8+wpa81/Newtonsoft.Json.xml",
        "lib/portable-net45+wp80+win8+wpa81+aspnetcore50/Newtonsoft.Json.dll",
        "lib/portable-net45+wp80+win8+wpa81+aspnetcore50/Newtonsoft.Json.xml",
        "tools/install.ps1"
      ]
    },
    "System.AppContext/4.0.0-beta-22725": {
      "serviceable": false,
      "sha": "AYmLhWVbThiZCdoB3WBc84+qIrxbWtIACLKwKUxpKlZjyfHI4BYGjdo0wlvNhA/caKF32ecGvLlo5JHqj0bDvQ==",
      "frameworks": {
        "DNX,Version=v4.5.1": {
          "dependencies": {
            "System.Runtime": "4.0.0-beta-22725"
          },
          "frameworkAssemblies": [],
          "runtimeAssemblies": [
            "lib/net45/System.AppContext.dll"
          ],
          "compileAssemblies": [
            "lib/net45/System.AppContext.dll"
          ]
        },
        "DNXCore,Version=v5.0": {
          "dependencies": {
            "System.Runtime": "4.0.0-beta-22725"
          },
          "frameworkAssemblies": [],
          "runtimeAssemblies": [
            "lib/aspnetcore50/System.AppContext.dll"
          ],
          "compileAssemblies": [
            "lib/contract/System.AppContext.dll"
          ]
        }
      },
      "files": [
        "License.rtf",
        "System.AppContext.4.0.0-beta-22725.nupkg",
        "System.AppContext.4.0.0-beta-22725.nupkg.sha512",
        "System.AppContext.nuspec",
        "lib/aspnetcore50/System.AppContext.dll",
        "lib/contract/System.AppContext.dll",
        "lib/net45/System.AppContext.dll",
        "lib/portable-wpa81+wp80+win80+net45+aspnetcore50/System.AppContext.dll"
      ]
    },
    "System.Collections/4.0.10-beta-22725": {
      "serviceable": false,
      "sha": "7jFfyyl/VmNK7TYMf3JSY0NndhaKpQC3XuLu20Uu3+Fuswe1GNZ1DoQpwF0qiEzso0rXA1jL6P3FlqYGfaIIIQ==",
      "frameworks": {
        "DNX,Version=v4.5.1": {
          "dependencies": {
            "System.Runtime": "4.0.0-beta-22725"
          },
          "frameworkAssemblies": [],
          "runtimeAssemblies": [
            "lib/net45/System.Collections.dll"
          ],
          "compileAssemblies": [
            "lib/net45/System.Collections.dll"
          ]
        },
        "DNXCore,Version=v5.0": {
          "dependencies": {
            "System.Runtime": "4.0.0-beta-22725"
          },
          "frameworkAssemblies": [],
          "runtimeAssemblies": [
            "lib/aspnetcore50/System.Collections.dll"
          ],
          "compileAssemblies": [
            "lib/contract/System.Collections.dll"
          ]
        }
      },
      "files": [
        "License.rtf",
        "System.Collections.4.0.10-beta-22725.nupkg",
        "System.Collections.4.0.10-beta-22725.nupkg.sha512",
        "System.Collections.nuspec",
        "lib/aspnetcore50/System.Collections.dll",
        "lib/contract/System.Collections.dll",
        "lib/net45/System.Collections.dll",
        "lib/portable-wpa81+wp80+win80+net45+aspnetcore50/System.Collections.dll"
      ]
    },
    "System.Collections.Concurrent/4.0.10-beta-22725": {
      "serviceable": false,
      "sha": "P7vLBHuPecjYTYpPeZshhLTmRZFSNuvJjYQiKVacTHqOd67mFwU3yo+MHcV/rQJIwSscLVA2lRcWEQqb2yb4OQ==",
      "frameworks": {
        "DNX,Version=v4.5.1": {
          "dependencies": {
            "System.Runtime": "4.0.0-beta-22725",
            "System.Threading.Tasks": "4.0.0-beta-22725"
          },
          "frameworkAssemblies": [],
          "runtimeAssemblies": [
            "lib/net45/System.Collections.Concurrent.dll"
          ],
          "compileAssemblies": [
            "lib/net45/System.Collections.Concurrent.dll"
          ]
        },
        "DNXCore,Version=v5.0": {
          "dependencies": {
            "System.Runtime": "4.0.0-beta-22725",
            "System.Threading.Tasks": "4.0.0-beta-22725"
          },
          "frameworkAssemblies": [],
          "runtimeAssemblies": [
            "lib/aspnetcore50/System.Collections.Concurrent.dll"
          ],
          "compileAssemblies": [
            "lib/contract/System.Collections.Concurrent.dll"
          ]
        }
      },
      "files": [
        "License.rtf",
        "System.Collections.Concurrent.4.0.10-beta-22725.nupkg",
        "System.Collections.Concurrent.4.0.10-beta-22725.nupkg.sha512",
        "System.Collections.Concurrent.nuspec",
        "lib/aspnetcore50/System.Collections.Concurrent.dll",
        "lib/contract/System.Collections.Concurrent.dll",
        "lib/net45/System.Collections.Concurrent.dll",
        "lib/portable-wpa81+wp80+win80+net45+aspnetcore50/System.Collections.Concurrent.dll"
      ]
    },
    "System.Collections.Immutable/1.1.33-beta": {
      "serviceable": true,
      "sha": "Qnv6M/BRf0w1xNoD5tH7V+jK0kdO+OZymwQS5Lj6FALt3AZMGVeJs+lHXi1PsKFll67UtGY+I7r8WDhRzspXCA==",
      "frameworks": {
        "DNX,Version=v4.5.1": {
          "dependencies": {},
          "frameworkAssemblies": [],
          "runtimeAssemblies": [
            "lib/portable-net45+win8+wp8+wpa81/System.Collections.Immutable.dll"
          ],
          "compileAssemblies": [
            "lib/portable-net45+win8+wp8+wpa81/System.Collections.Immutable.dll"
          ]
        },
        "DNXCore,Version=v5.0": {
          "dependencies": {},
          "frameworkAssemblies": [],
          "runtimeAssemblies": [
            "lib/portable-net45+win8+wp8+wpa81/System.Collections.Immutable.dll"
          ],
          "compileAssemblies": [
            "lib/portable-net45+win8+wp8+wpa81/System.Collections.Immutable.dll"
          ]
        }
      },
      "files": [
        "License-Stable.rtf",
        "System.Collections.Immutable.1.1.33-beta.nupkg",
        "System.Collections.Immutable.1.1.33-beta.nupkg.sha512",
        "System.Collections.Immutable.nuspec",
        "lib/portable-net45+win8+wp8+wpa81/System.Collections.Immutable.dll",
        "lib/portable-net45+win8+wp8+wpa81/System.Collections.Immutable.xml"
      ]
    },
    "System.ComponentModel/4.0.0-beta-22725": {
      "serviceable": false,
      "sha": "7oJyqWJ4YSdr5APrg4ls9o+5QgQ6k7G7mz15hvwGMxCyk08iK0PAgLPK+TwygzndVPAr1mWI9tTd9fgsAfxcHA==",
      "frameworks": {
        "DNX,Version=v4.5.1": {
          "dependencies": {
            "System.Runtime": "4.0.0-beta-22725"
          },
          "frameworkAssemblies": [],
          "runtimeAssemblies": [
            "lib/net45/System.ComponentModel.dll"
          ],
          "compileAssemblies": [
            "lib/net45/System.ComponentModel.dll"
          ]
        },
        "DNXCore,Version=v5.0": {
          "dependencies": {
            "System.Runtime": "4.0.0-beta-22725"
          },
          "frameworkAssemblies": [],
          "runtimeAssemblies": [
            "lib/aspnetcore50/System.ComponentModel.dll"
          ],
          "compileAssemblies": [
            "lib/contract/System.ComponentModel.dll"
          ]
        }
      },
      "files": [
        "License.rtf",
        "System.ComponentModel.4.0.0-beta-22725.nupkg",
        "System.ComponentModel.4.0.0-beta-22725.nupkg.sha512",
        "System.ComponentModel.nuspec",
        "lib/aspnetcore50/System.ComponentModel.dll",
        "lib/contract/System.ComponentModel.dll",
        "lib/net45/System.ComponentModel.dll",
        "lib/portable-wpa81+wp80+win80+net45+aspnetcore50/System.ComponentModel.dll"
      ]
    },
    "System.Diagnostics.Tools/4.0.0-beta-22725": {
      "serviceable": false,
      "sha": "zHeIKYjlNL4qH4QWg6h7+LaauKGYvhghR7ozoA5XGGFOht9ytse7c/tgHA5dIQHWEjoghH5m+adnqMY0Qk5+xA==",
      "frameworks": {
        "DNX,Version=v4.5.1": {
          "dependencies": {
            "System.Runtime": "4.0.0-beta-22725"
          },
          "frameworkAssemblies": [],
          "runtimeAssemblies": [
            "lib/net45/System.Diagnostics.Tools.dll"
          ],
          "compileAssemblies": [
            "lib/net45/System.Diagnostics.Tools.dll"
          ]
        },
        "DNXCore,Version=v5.0": {
          "dependencies": {
            "System.Runtime": "4.0.0-beta-22725"
          },
          "frameworkAssemblies": [],
          "runtimeAssemblies": [
            "lib/aspnetcore50/System.Diagnostics.Tools.dll"
          ],
          "compileAssemblies": [
            "lib/contract/System.Diagnostics.Tools.dll"
          ]
        }
      },
      "files": [
        "License.rtf",
        "System.Diagnostics.Tools.4.0.0-beta-22725.nupkg",
        "System.Diagnostics.Tools.4.0.0-beta-22725.nupkg.sha512",
        "System.Diagnostics.Tools.nuspec",
        "lib/aspnetcore50/System.Diagnostics.Tools.dll",
        "lib/contract/System.Diagnostics.Tools.dll",
        "lib/net45/System.Diagnostics.Tools.dll",
        "lib/portable-wpa81+wp80+win80+net45+aspnetcore50/System.Diagnostics.Tools.dll"
      ]
    },
    "System.Dynamic.Runtime/4.0.10-beta-22725": {
      "serviceable": false,
      "sha": "qXd8SDteZWZNHT++/tn8I4bj4Cu0CmwKnww1QinwhtRt7zPP/p3xoUDTl9XwsxWfRCnyvBoH6cRRvgf/C+8Hig==",
      "frameworks": {
        "DNX,Version=v4.5.1": {
          "dependencies": {
            "System.Linq.Expressions": "4.0.10-beta-22725",
            "System.ObjectModel": "4.0.0-beta-22725",
            "System.Reflection": "4.0.0-beta-22725",
            "System.Runtime": "4.0.20-beta-22725"
          },
          "frameworkAssemblies": [],
          "runtimeAssemblies": [
            "lib/net45/System.Dynamic.Runtime.dll"
          ],
          "compileAssemblies": [
            "lib/net45/System.Dynamic.Runtime.dll"
          ]
        },
        "DNXCore,Version=v5.0": {
          "dependencies": {
            "System.Linq.Expressions": "4.0.10-beta-22725",
            "System.ObjectModel": "4.0.0-beta-22725",
            "System.Reflection": "4.0.0-beta-22725",
            "System.Runtime": "4.0.20-beta-22725"
          },
          "frameworkAssemblies": [],
          "runtimeAssemblies": [
            "lib/aspnetcore50/System.Dynamic.Runtime.dll"
          ],
          "compileAssemblies": [
            "lib/contract/System.Dynamic.Runtime.dll"
          ]
        }
      },
      "files": [
        "License.rtf",
        "System.Dynamic.Runtime.4.0.10-beta-22725.nupkg",
        "System.Dynamic.Runtime.4.0.10-beta-22725.nupkg.sha512",
        "System.Dynamic.Runtime.nuspec",
        "lib/aspnetcore50/System.Dynamic.Runtime.dll",
        "lib/contract/System.Dynamic.Runtime.dll",
        "lib/net45/System.Dynamic.Runtime.dll",
        "lib/portable-wpa81+wp80+win80+net45+aspnetcore50/System.Dynamic.Runtime.dll"
      ]
    },
    "System.Globalization/4.0.10-beta-22725": {
      "serviceable": false,
      "sha": "7w4mfZzRUDuFpme94C/HfecdcU9f5uUwv+2j+xCRN/6OEvJZHm2Hbe0w8qwP26Q6f3N8eIDAPYr+mKpunJaDAA==",
      "frameworks": {
        "DNX,Version=v4.5.1": {
          "dependencies": {
            "System.Runtime": "4.0.0-beta-22725"
          },
          "frameworkAssemblies": [],
          "runtimeAssemblies": [
            "lib/net45/System.Globalization.dll"
          ],
          "compileAssemblies": [
            "lib/net45/System.Globalization.dll"
          ]
        },
        "DNXCore,Version=v5.0": {
          "dependencies": {
            "System.Runtime": "4.0.0-beta-22725"
          },
          "frameworkAssemblies": [],
          "runtimeAssemblies": [
            "lib/aspnetcore50/System.Globalization.dll"
          ],
          "compileAssemblies": [
            "lib/contract/System.Globalization.dll"
          ]
        }
      },
      "files": [
        "License.rtf",
        "System.Globalization.4.0.10-beta-22725.nupkg",
        "System.Globalization.4.0.10-beta-22725.nupkg.sha512",
        "System.Globalization.nuspec",
        "lib/aspnetcore50/System.Globalization.dll",
        "lib/contract/System.Globalization.dll",
        "lib/net45/System.Globalization.dll",
        "lib/portable-wpa81+wp80+win80+net45+aspnetcore50/System.Globalization.dll"
      ]
    },
    "System.IO/4.0.10-beta-22725": {
      "serviceable": false,
      "sha": "fPKD6NR9SH6mvgrU2eMXhkRBuARb6Xm+FsTvBwlYFzmVuHDRsDDyin9YFup5NwIvXXn7zl+br1l36tIvm49Svg==",
      "frameworks": {
        "DNX,Version=v4.5.1": {
          "dependencies": {
            "System.Runtime": "4.0.20-beta-22725",
            "System.Text.Encoding": "4.0.0-beta-22725",
            "System.Threading.Tasks": "4.0.0-beta-22725"
          },
          "frameworkAssemblies": [],
          "runtimeAssemblies": [
            "lib/net45/System.IO.dll"
          ],
          "compileAssemblies": [
            "lib/net45/System.IO.dll"
          ]
        },
        "DNXCore,Version=v5.0": {
          "dependencies": {
            "System.Runtime": "4.0.20-beta-22725",
            "System.Text.Encoding": "4.0.0-beta-22725",
            "System.Threading.Tasks": "4.0.0-beta-22725"
          },
          "frameworkAssemblies": [],
          "runtimeAssemblies": [
            "lib/aspnetcore50/System.IO.dll"
          ],
          "compileAssemblies": [
            "lib/contract/System.IO.dll"
          ]
        }
      },
      "files": [
        "License.rtf",
        "System.IO.4.0.10-beta-22725.nupkg",
        "System.IO.4.0.10-beta-22725.nupkg.sha512",
        "System.IO.nuspec",
        "lib/aspnetcore50/System.IO.dll",
        "lib/contract/System.IO.dll",
        "lib/net45/System.IO.dll",
        "lib/portable-wpa81+wp80+win80+net45+aspnetcore50/System.IO.dll"
      ]
    },
    "System.IO.Compression/4.0.0-beta-22725": {
      "serviceable": false,
      "sha": "tEqjo9vZGnyG+JzZzpUidTfvjertOhUwfZq18WWD5yyp5whjfVzoTfl6EBBAohg1DusdYu+sB03+MtyLHijzzw==",
      "frameworks": {
        "DNX,Version=v4.5.1": {
          "dependencies": {
            "System.IO": "4.0.0-beta-22725",
            "System.Runtime": "4.0.0-beta-22725",
            "System.Text.Encoding": "4.0.0-beta-22725"
          },
          "frameworkAssemblies": [],
          "runtimeAssemblies": [],
          "compileAssemblies": []
        },
        "DNXCore,Version=v5.0": {
          "dependencies": {
            "System.IO": "4.0.0-beta-22725",
            "System.Runtime": "4.0.0-beta-22725",
            "System.Text.Encoding": "4.0.0-beta-22725"
          },
          "frameworkAssemblies": [],
          "runtimeAssemblies": [
            "lib/aspnetcore50/System.IO.Compression.dll"
          ],
          "compileAssemblies": [
            "lib/contract/System.IO.Compression.dll"
          ]
        }
      },
      "files": [
        "License.rtf",
        "System.IO.Compression.4.0.0-beta-22725.nupkg",
        "System.IO.Compression.4.0.0-beta-22725.nupkg.sha512",
        "System.IO.Compression.nuspec",
        "lib/aspnetcore50/System.IO.Compression.dll",
        "lib/contract/System.IO.Compression.dll",
        "lib/net45/_._",
        "lib/portable-wpa81+wp80+win80+net45+aspnetcore50/System.IO.Compression.dll"
      ]
    },
    "System.IO.FileSystem/4.0.0-beta-22725": {
      "serviceable": false,
      "sha": "4XHELzoXiZUaEe4wrmoyk6RWaRachm2o/jwa9PtvsqiP+pPpDTuOCgEUvj4Fkl2vC72+BU1D8U/QILwSrSjWhA==",
      "frameworks": {
        "DNX,Version=v4.5.1": {
          "dependencies": {
            "System.IO": "4.0.0-beta-22725",
            "System.IO.FileSystem.Primitives": "4.0.0-beta-22725",
            "System.Runtime": "4.0.0-beta-22725",
            "System.Runtime.Handles": "4.0.0-beta-22725",
            "System.Text.Encoding": "4.0.0-beta-22725",
            "System.Threading.Tasks": "4.0.0-beta-22725"
          },
          "frameworkAssemblies": [],
          "runtimeAssemblies": [
            "lib/net45/System.IO.FileSystem.dll"
          ],
          "compileAssemblies": [
            "lib/net45/System.IO.FileSystem.dll"
          ]
        },
        "DNXCore,Version=v5.0": {
          "dependencies": {
            "System.IO": "4.0.0-beta-22725",
            "System.IO.FileSystem.Primitives": "4.0.0-beta-22725",
            "System.Runtime": "4.0.0-beta-22725",
            "System.Runtime.Handles": "4.0.0-beta-22725",
            "System.Text.Encoding": "4.0.0-beta-22725",
            "System.Threading.Tasks": "4.0.0-beta-22725"
          },
          "frameworkAssemblies": [],
          "runtimeAssemblies": [
            "lib/aspnetcore50/System.IO.FileSystem.dll"
          ],
          "compileAssemblies": [
            "lib/contract/System.IO.FileSystem.dll"
          ]
        }
      },
      "files": [
        "License.rtf",
        "System.IO.FileSystem.4.0.0-beta-22725.nupkg",
        "System.IO.FileSystem.4.0.0-beta-22725.nupkg.sha512",
        "System.IO.FileSystem.nuspec",
        "lib/aspnetcore50/System.IO.FileSystem.dll",
        "lib/contract/System.IO.FileSystem.dll",
        "lib/net45/System.IO.FileSystem.dll",
        "lib/portable-wpa81+wp80+win80+net45+aspnetcore50/System.IO.FileSystem.dll"
      ]
    },
    "System.IO.FileSystem.Primitives/4.0.0-beta-22725": {
      "serviceable": false,
      "sha": "ZROoDTlmHU8UPE/lZssTx4Yb4OqmEtv98uzxmjN5RauILn8c1+M1npyTom5R852YmTjJktK2FY8Caty09sqlTg==",
      "frameworks": {
        "DNX,Version=v4.5.1": {
          "dependencies": {
            "System.Runtime": "4.0.0-beta-22725"
          },
          "frameworkAssemblies": [],
          "runtimeAssemblies": [
            "lib/net45/System.IO.FileSystem.Primitives.dll"
          ],
          "compileAssemblies": [
            "lib/net45/System.IO.FileSystem.Primitives.dll"
          ]
        },
        "DNXCore,Version=v5.0": {
          "dependencies": {
            "System.Runtime": "4.0.0-beta-22725"
          },
          "frameworkAssemblies": [],
          "runtimeAssemblies": [
            "lib/aspnetcore50/System.IO.FileSystem.Primitives.dll"
          ],
          "compileAssemblies": [
            "lib/contract/System.IO.FileSystem.Primitives.dll"
          ]
        }
      },
      "files": [
        "License.rtf",
        "System.IO.FileSystem.Primitives.4.0.0-beta-22725.nupkg",
        "System.IO.FileSystem.Primitives.4.0.0-beta-22725.nupkg.sha512",
        "System.IO.FileSystem.Primitives.nuspec",
        "lib/aspnetcore50/System.IO.FileSystem.Primitives.dll",
        "lib/contract/System.IO.FileSystem.Primitives.dll",
        "lib/net45/System.IO.FileSystem.Primitives.dll",
        "lib/portable-wpa81+wp80+win80+net45+aspnetcore50/System.IO.FileSystem.Primitives.dll"
      ]
    },
    "System.IO.FileSystem.Watcher/4.0.0-beta-22725": {
      "serviceable": false,
      "sha": "QnXawDzCWeCJ2a+CbHAvEWsjQVp3Wea/NVGF1k4Ii76nGpGXn9F71OeP6fBbkypFPdsJIN+39Cp3ckYJHgKBBQ==",
      "frameworks": {
        "DNX,Version=v4.5.1": {
          "dependencies": {
            "System.Runtime": "4.0.0-beta-22725"
          },
          "frameworkAssemblies": [],
          "runtimeAssemblies": [
            "lib/net45/System.IO.FileSystem.Watcher.dll"
          ],
          "compileAssemblies": [
            "lib/net45/System.IO.FileSystem.Watcher.dll"
          ]
        },
        "DNXCore,Version=v5.0": {
          "dependencies": {
            "System.Runtime": "4.0.0-beta-22725"
          },
          "frameworkAssemblies": [],
          "runtimeAssemblies": [
            "lib/aspnetcore50/System.IO.FileSystem.Watcher.dll"
          ],
          "compileAssemblies": [
            "lib/contract/System.IO.FileSystem.Watcher.dll"
          ]
        }
      },
      "files": [
        "License.rtf",
        "System.IO.FileSystem.Watcher.4.0.0-beta-22725.nupkg",
        "System.IO.FileSystem.Watcher.4.0.0-beta-22725.nupkg.sha512",
        "System.IO.FileSystem.Watcher.nuspec",
        "lib/aspnetcore50/System.IO.FileSystem.Watcher.dll",
        "lib/contract/System.IO.FileSystem.Watcher.dll",
        "lib/net45/System.IO.FileSystem.Watcher.dll",
        "lib/portable-wpa81+wp80+win80+net45+aspnetcore50/System.IO.FileSystem.Watcher.dll"
      ]
    },
    "System.Linq/4.0.0-beta-22725": {
      "serviceable": false,
      "sha": "OyVdxY2qeecCWE5AY6fRx73XGVQCr9A4D2WSv/Wwq49zfA6PXZv807ZuSHeYhnEMeQ39qA9myEDbA8iNbM9CZA==",
      "frameworks": {
        "DNX,Version=v4.5.1": {
          "dependencies": {
            "System.Collections": "4.0.0-beta-22725",
            "System.Runtime": "4.0.0-beta-22725"
          },
          "frameworkAssemblies": [],
          "runtimeAssemblies": [
            "lib/net45/System.Linq.dll"
          ],
          "compileAssemblies": [
            "lib/net45/System.Linq.dll"
          ]
        },
        "DNXCore,Version=v5.0": {
          "dependencies": {
            "System.Collections": "4.0.0-beta-22725",
            "System.Runtime": "4.0.0-beta-22725"
          },
          "frameworkAssemblies": [],
          "runtimeAssemblies": [
            "lib/aspnetcore50/System.Linq.dll"
          ],
          "compileAssemblies": [
            "lib/contract/System.Linq.dll"
          ]
        }
      },
      "files": [
        "License.rtf",
        "System.Linq.4.0.0-beta-22725.nupkg",
        "System.Linq.4.0.0-beta-22725.nupkg.sha512",
        "System.Linq.nuspec",
        "lib/aspnetcore50/System.Linq.dll",
        "lib/contract/System.Linq.dll",
        "lib/net45/System.Linq.dll",
        "lib/portable-wpa81+wp80+win80+net45+aspnetcore50/System.Linq.dll"
      ]
    },
    "System.Linq.Expressions/4.0.10-beta-22725": {
      "serviceable": false,
      "sha": "o4rNbyJloawNxQQIeAo4YjZdC6S9Afa0xIik068CRUbDrdjydkW1iZ+gz1MrnBcHjYxzfFOu0xowtB4Gu+J4Yg==",
      "frameworks": {
        "DNX,Version=v4.5.1": {
          "dependencies": {
            "System.Reflection": "4.0.0-beta-22725",
            "System.Runtime": "4.0.0-beta-22725"
          },
          "frameworkAssemblies": [],
          "runtimeAssemblies": [
            "lib/net45/System.Linq.Expressions.dll"
          ],
          "compileAssemblies": [
            "lib/net45/System.Linq.Expressions.dll"
          ]
        },
        "DNXCore,Version=v5.0": {
          "dependencies": {
            "System.Reflection": "4.0.0-beta-22725",
            "System.Runtime": "4.0.0-beta-22725"
          },
          "frameworkAssemblies": [],
          "runtimeAssemblies": [
            "lib/aspnetcore50/System.Linq.Expressions.dll"
          ],
          "compileAssemblies": [
            "lib/contract/System.Linq.Expressions.dll"
          ]
        }
      },
      "files": [
        "License.rtf",
        "System.Linq.Expressions.4.0.10-beta-22725.nupkg",
        "System.Linq.Expressions.4.0.10-beta-22725.nupkg.sha512",
        "System.Linq.Expressions.nuspec",
        "lib/aspnetcore50/System.Linq.Expressions.dll",
        "lib/contract/System.Linq.Expressions.dll",
        "lib/net45/System.Linq.Expressions.dll",
        "lib/portable-wpa81+wp80+win80+net45+aspnetcore50/System.Linq.Expressions.dll"
      ]
    },
    "System.Net.Primitives/4.0.10-beta-22725": {
      "serviceable": false,
      "sha": "F4cbPC/2Ue/oY164e6pKZBCUggTIkJSXVpBZ/lS2lPdRyinNVLABs7R3ksejpNqA8Z23lB74gyJK/vk6CJQ0DA==",
      "frameworks": {
        "DNX,Version=v4.5.1": {
          "dependencies": {
            "System.Runtime": "4.0.0-beta-22725",
            "System.Runtime.Handles": "4.0.0-beta-22725"
          },
          "frameworkAssemblies": [],
          "runtimeAssemblies": [
            "lib/net45/System.Net.Primitives.dll"
          ],
          "compileAssemblies": [
            "lib/net45/System.Net.Primitives.dll"
          ]
        },
        "DNXCore,Version=v5.0": {
          "dependencies": {
            "System.Runtime": "4.0.0-beta-22725",
            "System.Runtime.Handles": "4.0.0-beta-22725"
          },
          "frameworkAssemblies": [],
          "runtimeAssemblies": [
            "lib/aspnetcore50/System.Net.Primitives.dll"
          ],
          "compileAssemblies": [
            "lib/contract/System.Net.Primitives.dll"
          ]
        }
      },
      "files": [
        "License.rtf",
        "System.Net.Primitives.4.0.10-beta-22725.nupkg",
        "System.Net.Primitives.4.0.10-beta-22725.nupkg.sha512",
        "System.Net.Primitives.nuspec",
        "lib/aspnetcore50/System.Net.Primitives.dll",
        "lib/contract/System.Net.Primitives.dll",
        "lib/net45/System.Net.Primitives.dll",
        "lib/portable-wpa81+wp80+win80+net45+aspnetcore50/System.Net.Primitives.dll"
      ]
    },
    "System.Net.Sockets/4.0.0-beta-22725": {
      "serviceable": false,
      "sha": "y+kF0kLUOXZqdJx3xOHcLZrb2d1UH/PcBq6cfPUbxJP4mRVwGS9ZKOinU2FH+ZLDkwXDw4NYrCuHp2KqARA+vQ==",
      "frameworks": {
        "DNX,Version=v4.5.1": {
          "dependencies": {
            "System.IO": "4.0.0-beta-22725",
            "System.Net.Primitives": "4.0.10-beta-22725",
            "System.Runtime": "4.0.0-beta-22725",
            "System.Threading.Tasks": "4.0.0-beta-22725"
          },
          "frameworkAssemblies": [],
          "runtimeAssemblies": [
            "lib/net45/System.Net.Sockets.dll"
          ],
          "compileAssemblies": [
            "lib/net45/System.Net.Sockets.dll"
          ]
        },
        "DNXCore,Version=v5.0": {
          "dependencies": {
            "System.IO": "4.0.0-beta-22725",
            "System.Net.Primitives": "4.0.10-beta-22725",
            "System.Runtime": "4.0.0-beta-22725",
            "System.Threading.Tasks": "4.0.0-beta-22725"
          },
          "frameworkAssemblies": [],
          "runtimeAssemblies": [
            "lib/aspnetcore50/System.Net.Sockets.dll"
          ],
          "compileAssemblies": [
            "lib/contract/System.Net.Sockets.dll"
          ]
        }
      },
      "files": [
        "License.rtf",
        "System.Net.Sockets.4.0.0-beta-22725.nupkg",
        "System.Net.Sockets.4.0.0-beta-22725.nupkg.sha512",
        "System.Net.Sockets.nuspec",
        "lib/aspnetcore50/System.Net.Sockets.dll",
        "lib/contract/System.Net.Sockets.dll",
        "lib/net45/System.Net.Sockets.dll",
        "lib/portable-wpa81+wp80+win80+net45+aspnetcore50/System.Net.Sockets.dll"
      ]
    },
    "System.ObjectModel/4.0.10-beta-22231": {
      "serviceable": false,
      "sha": "PJO5fntWZZsHOH8u8hlLrF3agnziX2nF1bvbiUPueN+Y6KPI9gAonvBpW+Jv1BiqCgVjnMur5rbW10CbqvKgXw==",
      "frameworks": {
        "DNX,Version=v4.5.1": {
          "dependencies": {
            "System.Runtime": "4.0.0-beta-22231"
          },
          "frameworkAssemblies": [],
          "runtimeAssemblies": [],
          "compileAssemblies": []
        },
        "DNXCore,Version=v5.0": {
          "dependencies": {
            "System.Runtime": "4.0.0-beta-22231"
          },
          "frameworkAssemblies": [],
          "runtimeAssemblies": [
            "lib/aspnetcore50/System.ObjectModel.dll"
          ],
          "compileAssemblies": [
            "lib/contract/System.ObjectModel.dll"
          ]
        }
      },
      "files": [
        "License.rtf",
        "System.ObjectModel.4.0.10-beta-22231.nupkg",
        "System.ObjectModel.4.0.10-beta-22231.nupkg.sha512",
        "System.ObjectModel.nuspec",
        "lib/aspnetcore50/System.ObjectModel.dll",
        "lib/contract/System.ObjectModel.dll"
      ]
    },
    "System.Reflection/4.0.10-beta-22725": {
      "serviceable": false,
      "sha": "TIKoPt7u5HmiX91gDvdM0Y3jrV8qvbc3Vv9dBlu3LzzV7xmwLbhqwQq8Ac18rQUGj6CVtFeLl50lLr8JbRH3xQ==",
      "frameworks": {
        "DNX,Version=v4.5.1": {
          "dependencies": {
            "System.IO": "4.0.0-beta-22725",
            "System.Reflection.Primitives": "4.0.0-beta-22725",
            "System.Runtime": "4.0.20-beta-22725"
          },
          "frameworkAssemblies": [],
          "runtimeAssemblies": [
            "lib/net45/System.Reflection.dll"
          ],
          "compileAssemblies": [
            "lib/net45/System.Reflection.dll"
          ]
        },
        "DNXCore,Version=v5.0": {
          "dependencies": {
            "System.IO": "4.0.0-beta-22725",
            "System.Reflection.Primitives": "4.0.0-beta-22725",
            "System.Runtime": "4.0.20-beta-22725"
          },
          "frameworkAssemblies": [],
          "runtimeAssemblies": [
            "lib/aspnetcore50/System.Reflection.dll"
          ],
          "compileAssemblies": [
            "lib/contract/System.Reflection.dll"
          ]
        }
      },
      "files": [
        "License.rtf",
        "System.Reflection.4.0.10-beta-22725.nupkg",
        "System.Reflection.4.0.10-beta-22725.nupkg.sha512",
        "System.Reflection.nuspec",
        "lib/aspnetcore50/System.Reflection.dll",
        "lib/contract/System.Reflection.dll",
        "lib/net45/System.Reflection.dll",
        "lib/portable-wpa81+wp80+win80+net45+aspnetcore50/System.Reflection.dll"
      ]
    },
    "System.Reflection.Emit/4.0.0-beta-22725": {
      "serviceable": false,
      "sha": "rL49KxaOVm1F0tdiKTHpSoLCbaNug/exdsWQivF9VhgKKKnLTX/2nCDAVsbkGLoBFPEabbo8mxEkOUokuCnfRw==",
      "frameworks": {
        "DNX,Version=v4.5.1": {
          "dependencies": {
            "System.IO": "4.0.0-beta-22725",
            "System.Reflection": "4.0.0-beta-22725",
            "System.Reflection.Emit.ILGeneration": "4.0.0-beta-22725",
            "System.Reflection.Primitives": "4.0.0-beta-22725",
            "System.Runtime": "4.0.0-beta-22725"
          },
          "frameworkAssemblies": [],
          "runtimeAssemblies": [
            "lib/net45/System.Reflection.Emit.dll"
          ],
          "compileAssemblies": [
            "lib/net45/System.Reflection.Emit.dll"
          ]
        },
        "DNXCore,Version=v5.0": {
          "dependencies": {
            "System.IO": "4.0.0-beta-22725",
            "System.Reflection": "4.0.0-beta-22725",
            "System.Reflection.Emit.ILGeneration": "4.0.0-beta-22725",
            "System.Reflection.Primitives": "4.0.0-beta-22725",
            "System.Runtime": "4.0.0-beta-22725"
          },
          "frameworkAssemblies": [],
          "runtimeAssemblies": [
            "lib/aspnetcore50/System.Reflection.Emit.dll"
          ],
          "compileAssemblies": [
            "lib/contract/System.Reflection.Emit.dll"
          ]
        }
      },
      "files": [
        "License.rtf",
        "System.Reflection.Emit.4.0.0-beta-22725.nupkg",
        "System.Reflection.Emit.4.0.0-beta-22725.nupkg.sha512",
        "System.Reflection.Emit.nuspec",
        "lib/aspnetcore50/System.Reflection.Emit.dll",
        "lib/contract/System.Reflection.Emit.dll",
        "lib/net45/System.Reflection.Emit.dll",
        "lib/portable-wpa81+wp80+win80+net45+aspnetcore50/System.Reflection.Emit.dll"
      ]
    },
    "System.Reflection.Emit.ILGeneration/4.0.0-beta-22725": {
      "serviceable": false,
      "sha": "x23Yr2pozEFzcaISc9PgLQI7KXl7IjsntEMGJNsG3XeO6qGOiXK4nbUpAEPZZR2sOv+O2uUyHZwyv1COdBfS6Q==",
      "frameworks": {
        "DNX,Version=v4.5.1": {
          "dependencies": {
            "System.Reflection": "4.0.0-beta-22725",
            "System.Reflection.Primitives": "4.0.0-beta-22725",
            "System.Runtime": "4.0.0-beta-22725"
          },
          "frameworkAssemblies": [],
          "runtimeAssemblies": [
            "lib/net45/System.Reflection.Emit.ILGeneration.dll"
          ],
          "compileAssemblies": [
            "lib/net45/System.Reflection.Emit.ILGeneration.dll"
          ]
        },
        "DNXCore,Version=v5.0": {
          "dependencies": {
            "System.Reflection": "4.0.0-beta-22725",
            "System.Reflection.Primitives": "4.0.0-beta-22725",
            "System.Runtime": "4.0.0-beta-22725"
          },
          "frameworkAssemblies": [],
          "runtimeAssemblies": [
            "lib/aspnetcore50/System.Reflection.Emit.ILGeneration.dll"
          ],
          "compileAssemblies": [
            "lib/contract/System.Reflection.Emit.ILGeneration.dll"
          ]
        }
      },
      "files": [
        "License.rtf",
        "System.Reflection.Emit.ILGeneration.4.0.0-beta-22725.nupkg",
        "System.Reflection.Emit.ILGeneration.4.0.0-beta-22725.nupkg.sha512",
        "System.Reflection.Emit.ILGeneration.nuspec",
        "lib/aspnetcore50/System.Reflection.Emit.ILGeneration.dll",
        "lib/contract/System.Reflection.Emit.ILGeneration.dll",
        "lib/net45/System.Reflection.Emit.ILGeneration.dll",
        "lib/portable-wpa81+wp80+win80+net45+aspnetcore50/System.Reflection.Emit.ILGeneration.dll"
      ]
    },
    "System.Reflection.Emit.Lightweight/4.0.0-beta-22725": {
      "serviceable": false,
      "sha": "zRRADYw3qfanvyEjQxi6My3dWsVZSYwUBvYe7ZgTBZBAdRquGXLqaJZ8MFOBvdHiVcSZxEx2xzfhmXkNioaQog==",
      "frameworks": {
        "DNX,Version=v4.5.1": {
          "dependencies": {
            "System.Reflection": "4.0.0-beta-22725",
            "System.Reflection.Emit.ILGeneration": "4.0.0-beta-22725",
            "System.Reflection.Primitives": "4.0.0-beta-22725",
            "System.Runtime": "4.0.0-beta-22725"
          },
          "frameworkAssemblies": [],
          "runtimeAssemblies": [
            "lib/net45/System.Reflection.Emit.Lightweight.dll"
          ],
          "compileAssemblies": [
            "lib/net45/System.Reflection.Emit.Lightweight.dll"
          ]
        },
        "DNXCore,Version=v5.0": {
          "dependencies": {
            "System.Reflection": "4.0.0-beta-22725",
            "System.Reflection.Emit.ILGeneration": "4.0.0-beta-22725",
            "System.Reflection.Primitives": "4.0.0-beta-22725",
            "System.Runtime": "4.0.0-beta-22725"
          },
          "frameworkAssemblies": [],
          "runtimeAssemblies": [
            "lib/aspnetcore50/System.Reflection.Emit.Lightweight.dll"
          ],
          "compileAssemblies": [
            "lib/contract/System.Reflection.Emit.Lightweight.dll"
          ]
        }
      },
      "files": [
        "License.rtf",
        "System.Reflection.Emit.Lightweight.4.0.0-beta-22725.nupkg",
        "System.Reflection.Emit.Lightweight.4.0.0-beta-22725.nupkg.sha512",
        "System.Reflection.Emit.Lightweight.nuspec",
        "lib/aspnetcore50/System.Reflection.Emit.Lightweight.dll",
        "lib/contract/System.Reflection.Emit.Lightweight.dll",
        "lib/net45/System.Reflection.Emit.Lightweight.dll",
        "lib/portable-wpa81+wp80+win80+net45+aspnetcore50/System.Reflection.Emit.Lightweight.dll"
      ]
    },
    "System.Reflection.Extensions/4.0.0-beta-22725": {
      "serviceable": false,
      "sha": "H9MdMH3VxzfGhOK+6Ske8lk/svE1B70obM7A7F84M1erZ52rvq9jiTMplg/7huBbdzzJhI5kWQjiWLAriL7hvw==",
      "frameworks": {
        "DNX,Version=v4.5.1": {
          "dependencies": {
            "System.Reflection": "4.0.0-beta-22725",
            "System.Runtime": "4.0.0-beta-22725"
          },
          "frameworkAssemblies": [],
          "runtimeAssemblies": [
            "lib/net45/System.Reflection.Extensions.dll"
          ],
          "compileAssemblies": [
            "lib/net45/System.Reflection.Extensions.dll"
          ]
        },
        "DNXCore,Version=v5.0": {
          "dependencies": {
            "System.Reflection": "4.0.0-beta-22725",
            "System.Runtime": "4.0.0-beta-22725"
          },
          "frameworkAssemblies": [],
          "runtimeAssemblies": [
            "lib/aspnetcore50/System.Reflection.Extensions.dll"
          ],
          "compileAssemblies": [
            "lib/contract/System.Reflection.Extensions.dll"
          ]
        }
      },
      "files": [
        "License.rtf",
        "System.Reflection.Extensions.4.0.0-beta-22725.nupkg",
        "System.Reflection.Extensions.4.0.0-beta-22725.nupkg.sha512",
        "System.Reflection.Extensions.nuspec",
        "lib/aspnetcore50/System.Reflection.Extensions.dll",
        "lib/contract/System.Reflection.Extensions.dll",
        "lib/net45/System.Reflection.Extensions.dll",
        "lib/portable-wpa81+wp80+win80+net45+aspnetcore50/System.Reflection.Extensions.dll"
      ]
    },
    "System.Reflection.Metadata/1.0.18-beta": {
      "serviceable": true,
      "sha": "4PtC2U6seQthZMvXvGTxXZUqlF0oV9jzYNTkG0Yo/D6cLO5AH3lrxh2djGyKsDYnAZjBCoyA/z3vHRCeaBEp4w==",
      "frameworks": {
        "DNX,Version=v4.5.1": {
          "dependencies": {
            "System.Collections.Immutable": "1.1.33-beta"
          },
          "frameworkAssemblies": [],
          "runtimeAssemblies": [
            "lib/portable-net45+win8/System.Reflection.Metadata.dll"
          ],
          "compileAssemblies": [
            "lib/portable-net45+win8/System.Reflection.Metadata.dll"
          ]
        },
        "DNXCore,Version=v5.0": {
          "dependencies": {
            "System.Collections.Immutable": "1.1.33-beta"
          },
          "frameworkAssemblies": [],
          "runtimeAssemblies": [
            "lib/portable-net45+win8/System.Reflection.Metadata.dll"
          ],
          "compileAssemblies": [
            "lib/portable-net45+win8/System.Reflection.Metadata.dll"
          ]
        }
      },
      "files": [
        "License-Stable.rtf",
        "System.Reflection.Metadata.1.0.18-beta.nupkg",
        "System.Reflection.Metadata.1.0.18-beta.nupkg.sha512",
        "System.Reflection.Metadata.nuspec",
        "lib/portable-net45+win8/System.Reflection.Metadata.dll",
        "lib/portable-net45+win8/System.Reflection.Metadata.xml"
      ]
    },
    "System.Reflection.Primitives/4.0.0-beta-22725": {
      "serviceable": false,
      "sha": "OAMsDvdHi3QH+Fiq3xybWxTOJg2p0CDroiQhyPKfHSvpnpPxYkB9QpVnX4DMvJAI9KLDfhMMeKdwwQpTL7JIpQ==",
      "frameworks": {
        "DNX,Version=v4.5.1": {
          "dependencies": {
            "System.Runtime": "4.0.0-beta-22725"
          },
          "frameworkAssemblies": [],
          "runtimeAssemblies": [
            "lib/net45/System.Reflection.Primitives.dll"
          ],
          "compileAssemblies": [
            "lib/net45/System.Reflection.Primitives.dll"
          ]
        },
        "DNXCore,Version=v5.0": {
          "dependencies": {
            "System.Runtime": "4.0.0-beta-22725"
          },
          "frameworkAssemblies": [],
          "runtimeAssemblies": [
            "lib/aspnetcore50/System.Reflection.Primitives.dll"
          ],
          "compileAssemblies": [
            "lib/contract/System.Reflection.Primitives.dll"
          ]
        }
      },
      "files": [
        "License.rtf",
        "System.Reflection.Primitives.4.0.0-beta-22725.nupkg",
        "System.Reflection.Primitives.4.0.0-beta-22725.nupkg.sha512",
        "System.Reflection.Primitives.nuspec",
        "lib/aspnetcore50/System.Reflection.Primitives.dll",
        "lib/contract/System.Reflection.Primitives.dll",
        "lib/net45/System.Reflection.Primitives.dll",
        "lib/portable-wpa81+wp80+win80+net45+aspnetcore50/System.Reflection.Primitives.dll"
      ]
    },
    "System.Reflection.TypeExtensions/4.0.0-beta-22725": {
      "serviceable": false,
      "sha": "NDie8o/Qu5GpK+0MIdKC4TE2qAfWWETimLrWbu9NA2WNsmDTFSpFeQNNvTa/IP+9LEcJmXFL/a41sMFdVEoNFg==",
      "frameworks": {
        "DNX,Version=v4.5.1": {
          "dependencies": {
            "System.Reflection": "4.0.0-beta-22725",
            "System.Runtime": "4.0.0-beta-22725"
          },
          "frameworkAssemblies": [],
          "runtimeAssemblies": [],
          "compileAssemblies": []
        },
        "DNXCore,Version=v5.0": {
          "dependencies": {
            "System.Reflection": "4.0.0-beta-22725",
            "System.Runtime": "4.0.0-beta-22725"
          },
          "frameworkAssemblies": [],
          "runtimeAssemblies": [
            "lib/aspnetcore50/System.Reflection.TypeExtensions.dll"
          ],
          "compileAssemblies": [
            "lib/contract/System.Reflection.TypeExtensions.dll"
          ]
        }
      },
      "files": [
        "License.rtf",
        "System.Reflection.TypeExtensions.4.0.0-beta-22725.nupkg",
        "System.Reflection.TypeExtensions.4.0.0-beta-22725.nupkg.sha512",
        "System.Reflection.TypeExtensions.nuspec",
        "lib/aspnetcore50/System.Reflection.TypeExtensions.dll",
        "lib/contract/System.Reflection.TypeExtensions.dll",
        "lib/net45/_._",
        "lib/portable-wpa81+wp80+win80+net45+aspnetcore50/System.Reflection.TypeExtensions.dll"
      ]
    },
    "System.Resources.ResourceManager/4.0.0-beta-22725": {
      "serviceable": false,
      "sha": "cBc/vbARpc6za/JKTWeaR3w2OIlDmhFqZx3BWeqbsbdY0zOYGO4INu8vinIEcNR+iz/cHLh+uMXXm0dpSjETPA==",
      "frameworks": {
        "DNX,Version=v4.5.1": {
          "dependencies": {
            "System.Globalization": "4.0.0-beta-22725",
            "System.Reflection": "4.0.0-beta-22725",
            "System.Runtime": "4.0.0-beta-22725"
          },
          "frameworkAssemblies": [],
          "runtimeAssemblies": [
            "lib/net45/System.Resources.ResourceManager.dll"
          ],
          "compileAssemblies": [
            "lib/net45/System.Resources.ResourceManager.dll"
          ]
        },
        "DNXCore,Version=v5.0": {
          "dependencies": {
            "System.Globalization": "4.0.0-beta-22725",
            "System.Reflection": "4.0.0-beta-22725",
            "System.Runtime": "4.0.0-beta-22725"
          },
          "frameworkAssemblies": [],
          "runtimeAssemblies": [
            "lib/aspnetcore50/System.Resources.ResourceManager.dll"
          ],
          "compileAssemblies": [
            "lib/contract/System.Resources.ResourceManager.dll"
          ]
        }
      },
      "files": [
        "License.rtf",
        "System.Resources.ResourceManager.4.0.0-beta-22725.nupkg",
        "System.Resources.ResourceManager.4.0.0-beta-22725.nupkg.sha512",
        "System.Resources.ResourceManager.nuspec",
        "lib/aspnetcore50/System.Resources.ResourceManager.dll",
        "lib/contract/System.Resources.ResourceManager.dll",
        "lib/net45/System.Resources.ResourceManager.dll",
        "lib/portable-wpa81+wp80+win80+net45+aspnetcore50/System.Resources.ResourceManager.dll"
      ]
    },
    "System.Resources.ResourceWriter/4.0.0-beta-22725": {
      "serviceable": false,
      "sha": "y7kjyL9ljXFYD2/4pIeQ64lt1wR26GACyLFksXmblp/ihVbX3XlhkQOHmKXFcxQMeMcdtX2mbnA1OvaXw1SCDQ==",
      "frameworks": {
        "DNX,Version=v4.5.1": {
          "dependencies": {
            "System.IO": "4.0.0-beta-22725",
            "System.Runtime": "4.0.0-beta-22725"
          },
          "frameworkAssemblies": [],
          "runtimeAssemblies": [
            "lib/net45/System.Resources.ResourceWriter.dll"
          ],
          "compileAssemblies": [
            "lib/net45/System.Resources.ResourceWriter.dll"
          ]
        },
        "DNXCore,Version=v5.0": {
          "dependencies": {
            "System.IO": "4.0.0-beta-22725",
            "System.Runtime": "4.0.0-beta-22725"
          },
          "frameworkAssemblies": [],
          "runtimeAssemblies": [
            "lib/aspnetcore50/System.Resources.ResourceWriter.dll"
          ],
          "compileAssemblies": [
            "lib/contract/System.Resources.ResourceWriter.dll"
          ]
        }
      },
      "files": [
        "License.rtf",
        "System.Resources.ResourceWriter.4.0.0-beta-22725.nupkg",
        "System.Resources.ResourceWriter.4.0.0-beta-22725.nupkg.sha512",
        "System.Resources.ResourceWriter.nuspec",
        "lib/aspnetcore50/System.Resources.ResourceWriter.dll",
        "lib/contract/System.Resources.ResourceWriter.dll",
        "lib/net45/System.Resources.ResourceWriter.dll",
        "lib/portable-wpa81+wp80+win80+net45+aspnetcore50/System.Resources.ResourceWriter.dll"
      ]
    },
    "System.Runtime/4.0.20-beta-22725": {
      "serviceable": false,
      "sha": "E+55rF8+hxvnil294CyRVlMS3SLDMlw6g7lgRprMSo8h00m+MFepwFCklnE0OABNnr9Z+CFw+3CHugjMudUecg==",
      "frameworks": {
        "DNX,Version=v4.5.1": {
          "dependencies": {},
          "frameworkAssemblies": [],
          "runtimeAssemblies": [
            "lib/net45/System.Runtime.dll"
          ],
          "compileAssemblies": [
            "lib/net45/System.Runtime.dll"
          ]
        },
        "DNXCore,Version=v5.0": {
          "dependencies": {},
          "frameworkAssemblies": [],
          "runtimeAssemblies": [
            "lib/aspnetcore50/System.Runtime.dll"
          ],
          "compileAssemblies": [
            "lib/contract/System.Runtime.dll"
          ]
        }
      },
      "files": [
        "License.rtf",
        "System.Runtime.4.0.20-beta-22725.nupkg",
        "System.Runtime.4.0.20-beta-22725.nupkg.sha512",
        "System.Runtime.nuspec",
        "lib/aspnetcore50/System.Runtime.dll",
        "lib/contract/System.Runtime.dll",
        "lib/net45/System.Runtime.dll",
        "lib/portable-wpa81+wp80+win80+net45+aspnetcore50/System.Runtime.dll"
      ]
    },
    "System.Runtime.Extensions/4.0.10-beta-22725": {
      "serviceable": false,
      "sha": "o47k3aHhCABgOcCp+R1TNHd7naTYmDt/dxOgqvLU2krmznt99YQqtPsMHY1LQprVgcSdy+zY5bG6lp6Z5Lrn0Q==",
      "frameworks": {
        "DNX,Version=v4.5.1": {
          "dependencies": {
            "System.Runtime": "4.0.20-beta-22725"
          },
          "frameworkAssemblies": [],
          "runtimeAssemblies": [
            "lib/net45/System.Runtime.Extensions.dll"
          ],
          "compileAssemblies": [
            "lib/net45/System.Runtime.Extensions.dll"
          ]
        },
        "DNXCore,Version=v5.0": {
          "dependencies": {
            "System.Runtime": "4.0.20-beta-22725"
          },
          "frameworkAssemblies": [],
          "runtimeAssemblies": [
            "lib/aspnetcore50/System.Runtime.Extensions.dll"
          ],
          "compileAssemblies": [
            "lib/contract/System.Runtime.Extensions.dll"
          ]
        }
      },
      "files": [
        "License.rtf",
        "System.Runtime.Extensions.4.0.10-beta-22725.nupkg",
        "System.Runtime.Extensions.4.0.10-beta-22725.nupkg.sha512",
        "System.Runtime.Extensions.nuspec",
        "lib/aspnetcore50/System.Runtime.Extensions.dll",
        "lib/contract/System.Runtime.Extensions.dll",
        "lib/net45/System.Runtime.Extensions.dll",
        "lib/portable-wpa81+wp80+win80+net45+aspnetcore50/System.Runtime.Extensions.dll"
      ]
    },
    "System.Runtime.Handles/4.0.0-beta-22725": {
      "serviceable": false,
      "sha": "P75LDduuQXiBEaZ2+/pF0cATLzXha9znQSReEoj2iJOO2dpqhPDCkZxPUDKg11n/Mb5haL4Ec9bu28CPZsqGhw==",
      "frameworks": {
        "DNX,Version=v4.5.1": {
          "dependencies": {
            "System.Runtime": "4.0.0-beta-22725"
          },
          "frameworkAssemblies": [],
          "runtimeAssemblies": [
            "lib/net45/System.Runtime.Handles.dll"
          ],
          "compileAssemblies": [
            "lib/net45/System.Runtime.Handles.dll"
          ]
        },
        "DNXCore,Version=v5.0": {
          "dependencies": {
            "System.Runtime": "4.0.0-beta-22725"
          },
          "frameworkAssemblies": [],
          "runtimeAssemblies": [
            "lib/aspnetcore50/System.Runtime.Handles.dll"
          ],
          "compileAssemblies": [
            "lib/contract/System.Runtime.Handles.dll"
          ]
        }
      },
      "files": [
        "License.rtf",
        "System.Runtime.Handles.4.0.0-beta-22725.nupkg",
        "System.Runtime.Handles.4.0.0-beta-22725.nupkg.sha512",
        "System.Runtime.Handles.nuspec",
        "lib/aspnetcore50/System.Runtime.Handles.dll",
        "lib/contract/System.Runtime.Handles.dll",
        "lib/net45/System.Runtime.Handles.dll",
        "lib/portable-wpa81+wp80+win80+net45+aspnetcore50/System.Runtime.Handles.dll"
      ]
    },
    "System.Runtime.InteropServices/4.0.20-beta-22725": {
      "serviceable": false,
      "sha": "4N/3tM1Upp0Sz5hlvJKSDJ4VyIdZcAPa3gKHpYmGeM5l6aVcR/94XAJf3QUlFEbA6wEK+60YtqOCCb64W2GNXw==",
      "frameworks": {
        "DNX,Version=v4.5.1": {
          "dependencies": {
            "System.Reflection": "4.0.0-beta-22725",
            "System.Reflection.Primitives": "4.0.0-beta-22725",
            "System.Runtime": "4.0.0-beta-22725",
            "System.Runtime.Handles": "4.0.0-beta-22725"
          },
          "frameworkAssemblies": [],
          "runtimeAssemblies": [
            "lib/net45/System.Runtime.InteropServices.dll"
          ],
          "compileAssemblies": [
            "lib/net45/System.Runtime.InteropServices.dll"
          ]
        },
        "DNXCore,Version=v5.0": {
          "dependencies": {
            "System.Reflection": "4.0.0-beta-22725",
            "System.Reflection.Primitives": "4.0.0-beta-22725",
            "System.Runtime": "4.0.0-beta-22725",
            "System.Runtime.Handles": "4.0.0-beta-22725"
          },
          "frameworkAssemblies": [],
          "runtimeAssemblies": [
            "lib/aspnetcore50/System.Runtime.InteropServices.dll"
          ],
          "compileAssemblies": [
            "lib/contract/System.Runtime.InteropServices.dll"
          ]
        }
      },
      "files": [
        "License.rtf",
        "System.Runtime.InteropServices.4.0.20-beta-22725.nupkg",
        "System.Runtime.InteropServices.4.0.20-beta-22725.nupkg.sha512",
        "System.Runtime.InteropServices.nuspec",
        "lib/aspnetcore50/System.Runtime.InteropServices.dll",
        "lib/contract/System.Runtime.InteropServices.dll",
        "lib/net45/System.Runtime.InteropServices.dll",
        "lib/portable-wpa81+wp80+win80+net45+aspnetcore50/System.Runtime.InteropServices.dll"
      ]
    },
    "System.Runtime.Loader/4.0.0-beta-22725": {
      "serviceable": false,
      "sha": "mhBLlhMitJX3trdjupKJ/9KrJt9WMFu+96a6/K1Yp1SJATNg2Im9hM8Du2Nl+9EsN83nd84JEF2/DZVjhYAM4Q==",
      "frameworks": {
        "DNX,Version=v4.5.1": {
          "dependencies": {
            "System.IO": "4.0.0-beta-22725",
            "System.Reflection": "4.0.0-beta-22725",
            "System.Runtime": "4.0.0-beta-22725"
          },
          "frameworkAssemblies": [],
          "runtimeAssemblies": [],
          "compileAssemblies": []
        },
        "DNXCore,Version=v5.0": {
          "dependencies": {
            "System.IO": "4.0.0-beta-22725",
            "System.Reflection": "4.0.0-beta-22725",
            "System.Runtime": "4.0.0-beta-22725"
          },
          "frameworkAssemblies": [],
          "runtimeAssemblies": [
            "lib/aspnetcore50/System.Runtime.Loader.dll"
          ],
          "compileAssemblies": [
            "lib/contract/System.Runtime.Loader.dll"
          ]
        }
      },
      "files": [
        "License.rtf",
        "System.Runtime.Loader.4.0.0-beta-22725.nupkg",
        "System.Runtime.Loader.4.0.0-beta-22725.nupkg.sha512",
        "System.Runtime.Loader.nuspec",
        "lib/aspnetcore50/System.Runtime.Loader.dll",
        "lib/contract/System.Runtime.Loader.dll",
        "lib/net45/_._",
        "lib/portable-wpa81+wp80+win80+net45+aspnetcore50/System.Runtime.Loader.dll"
      ]
    },
    "System.Text.Encoding/4.0.10-beta-22725": {
      "serviceable": false,
      "sha": "Jg5sM3H34dUj9PFrxK8wW7g5BsHrg2+n82xPx5lAy7oGcFxTTjzsk/EZd4Drwo5LM0NSZonuyogG3c6C4PfRHA==",
      "frameworks": {
        "DNX,Version=v4.5.1": {
          "dependencies": {
            "System.Runtime": "4.0.0-beta-22725"
          },
          "frameworkAssemblies": [],
          "runtimeAssemblies": [
            "lib/net45/System.Text.Encoding.dll"
          ],
          "compileAssemblies": [
            "lib/net45/System.Text.Encoding.dll"
          ]
        },
        "DNXCore,Version=v5.0": {
          "dependencies": {
            "System.Runtime": "4.0.0-beta-22725"
          },
          "frameworkAssemblies": [],
          "runtimeAssemblies": [
            "lib/aspnetcore50/System.Text.Encoding.dll"
          ],
          "compileAssemblies": [
            "lib/contract/System.Text.Encoding.dll"
          ]
        }
      },
      "files": [
        "License.rtf",
        "System.Text.Encoding.4.0.10-beta-22725.nupkg",
        "System.Text.Encoding.4.0.10-beta-22725.nupkg.sha512",
        "System.Text.Encoding.nuspec",
        "lib/aspnetcore50/System.Text.Encoding.dll",
        "lib/contract/System.Text.Encoding.dll",
        "lib/net45/System.Text.Encoding.dll",
        "lib/portable-wpa81+wp80+win80+net45+aspnetcore50/System.Text.Encoding.dll"
      ]
    },
    "System.Text.RegularExpressions/4.0.10-beta-22725": {
      "serviceable": false,
      "sha": "HOGazdKUk7dfCWwZnaPme16qCi/c53aB6zj+V9ujhg9bOBB+Kc46a5nFoE/98SjZu9d2uH4WElqzeMJzjzu1Ag==",
      "frameworks": {
        "DNX,Version=v4.5.1": {
          "dependencies": {
            "System.Runtime": "4.0.0-beta-22725"
          },
          "frameworkAssemblies": [],
          "runtimeAssemblies": [
            "lib/net45/System.Text.RegularExpressions.dll"
          ],
          "compileAssemblies": [
            "lib/net45/System.Text.RegularExpressions.dll"
          ]
        },
        "DNXCore,Version=v5.0": {
          "dependencies": {
            "System.Runtime": "4.0.0-beta-22725"
          },
          "frameworkAssemblies": [],
          "runtimeAssemblies": [
            "lib/aspnetcore50/System.Text.RegularExpressions.dll"
          ],
          "compileAssemblies": [
            "lib/contract/System.Text.RegularExpressions.dll"
          ]
        }
      },
      "files": [
        "License.rtf",
        "System.Text.RegularExpressions.4.0.10-beta-22725.nupkg",
        "System.Text.RegularExpressions.4.0.10-beta-22725.nupkg.sha512",
        "System.Text.RegularExpressions.nuspec",
        "lib/aspnetcore50/System.Text.RegularExpressions.dll",
        "lib/contract/System.Text.RegularExpressions.dll",
        "lib/net45/System.Text.RegularExpressions.dll",
        "lib/portable-wpa81+wp80+win80+net45+aspnetcore50/System.Text.RegularExpressions.dll"
      ]
    },
    "System.Threading/4.0.10-beta-22725": {
      "serviceable": false,
      "sha": "X0u27Gz7O8Pd7Ew1MGcCq46jtTnEiMCYfg6ka/Yy89Q5Vr6RmfGfXpTLQlaQlOoQlFKAlGMR9URIsinHCepKLA==",
      "frameworks": {
        "DNX,Version=v4.5.1": {
          "dependencies": {
            "System.Runtime": "4.0.0-beta-22725",
            "System.Threading.Tasks": "4.0.0-beta-22725"
          },
          "frameworkAssemblies": [],
          "runtimeAssemblies": [
            "lib/net45/System.Threading.dll"
          ],
          "compileAssemblies": [
            "lib/net45/System.Threading.dll"
          ]
        },
        "DNXCore,Version=v5.0": {
          "dependencies": {
            "System.Runtime": "4.0.0-beta-22725",
            "System.Threading.Tasks": "4.0.0-beta-22725"
          },
          "frameworkAssemblies": [],
          "runtimeAssemblies": [
            "lib/aspnetcore50/System.Threading.dll"
          ],
          "compileAssemblies": [
            "lib/contract/System.Threading.dll"
          ]
        }
      },
      "files": [
        "License.rtf",
        "System.Threading.4.0.10-beta-22725.nupkg",
        "System.Threading.4.0.10-beta-22725.nupkg.sha512",
        "System.Threading.nuspec",
        "lib/aspnetcore50/System.Threading.dll",
        "lib/contract/System.Threading.dll",
        "lib/net45/System.Threading.dll",
        "lib/portable-wpa81+wp80+win80+net45+aspnetcore50/System.Threading.dll"
      ]
    },
    "System.Threading.Tasks/4.0.10-beta-22725": {
      "serviceable": false,
      "sha": "VopzACu0/NVYK35nDbEaQqEvlM+9M3lHmVd8phXbRC9qPxynufTQkuR2CkRrCT8sWSWKHxEhOfwBR0KIuB6ptw==",
      "frameworks": {
        "DNX,Version=v4.5.1": {
          "dependencies": {
            "System.Runtime": "4.0.0-beta-22725"
          },
          "frameworkAssemblies": [],
          "runtimeAssemblies": [
            "lib/net45/System.Threading.Tasks.dll"
          ],
          "compileAssemblies": [
            "lib/net45/System.Threading.Tasks.dll"
          ]
        },
        "DNXCore,Version=v5.0": {
          "dependencies": {
            "System.Runtime": "4.0.0-beta-22725"
          },
          "frameworkAssemblies": [],
          "runtimeAssemblies": [
            "lib/aspnetcore50/System.Threading.Tasks.dll"
          ],
          "compileAssemblies": [
            "lib/contract/System.Threading.Tasks.dll"
          ]
        }
      },
      "files": [
        "License.rtf",
        "System.Threading.Tasks.4.0.10-beta-22725.nupkg",
        "System.Threading.Tasks.4.0.10-beta-22725.nupkg.sha512",
        "System.Threading.Tasks.nuspec",
        "lib/aspnetcore50/System.Threading.Tasks.dll",
        "lib/contract/System.Threading.Tasks.dll",
        "lib/net45/System.Threading.Tasks.dll",
        "lib/portable-wpa81+wp80+win80+net45+aspnetcore50/System.Threading.Tasks.dll"
      ]
    },
    "System.Threading.Thread/4.0.0-beta-22725": {
      "serviceable": false,
      "sha": "h7ZuoJ4MJyk7xeY6xNzucXM7BDaAPpABLkf4b4WnQTjpYi2EW2yV5FBTi1K5dEtEgQVTPx3X8kpvMP7wMY/WCQ==",
      "frameworks": {
        "DNX,Version=v4.5.1": {
          "dependencies": {
            "System.Runtime": "4.0.0-beta-22725"
          },
          "frameworkAssemblies": [],
          "runtimeAssemblies": [
            "lib/net45/System.Threading.Thread.dll"
          ],
          "compileAssemblies": [
            "lib/net45/System.Threading.Thread.dll"
          ]
        },
        "DNXCore,Version=v5.0": {
          "dependencies": {
            "System.Runtime": "4.0.0-beta-22725"
          },
          "frameworkAssemblies": [],
          "runtimeAssemblies": [
            "lib/aspnetcore50/System.Threading.Thread.dll"
          ],
          "compileAssemblies": [
            "lib/contract/System.Threading.Thread.dll"
          ]
        }
      },
      "files": [
        "License.rtf",
        "System.Threading.Thread.4.0.0-beta-22725.nupkg",
        "System.Threading.Thread.4.0.0-beta-22725.nupkg.sha512",
        "System.Threading.Thread.nuspec",
        "lib/aspnetcore50/System.Threading.Thread.dll",
        "lib/contract/System.Threading.Thread.dll",
        "lib/net45/System.Threading.Thread.dll",
        "lib/portable-wpa81+wp80+win80+net45+aspnetcore50/System.Threading.Thread.dll"
      ]
    },
    "System.Threading.ThreadPool/4.0.10-beta-22725": {
      "serviceable": false,
      "sha": "GXlvM7W3i/sjuKqybGi2IhY6SvrBCdwR5DauEN8Zwuk7gp7JCDuH78Z2Ab6mY0Zkyq9IUIjZ7pOA7VEFvrdVKg==",
      "frameworks": {
        "DNX,Version=v4.5.1": {
          "dependencies": {
            "System.Runtime": "4.0.0-beta-22725",
            "System.Runtime.InteropServices": "4.0.0-beta-22725"
          },
          "frameworkAssemblies": [],
          "runtimeAssemblies": [
            "lib/net45/System.Threading.ThreadPool.dll"
          ],
          "compileAssemblies": [
            "lib/net45/System.Threading.ThreadPool.dll"
          ]
        },
        "DNXCore,Version=v5.0": {
          "dependencies": {
            "System.Runtime": "4.0.0-beta-22725",
            "System.Runtime.InteropServices": "4.0.0-beta-22725"
          },
          "frameworkAssemblies": [],
          "runtimeAssemblies": [
            "lib/aspnetcore50/System.Threading.ThreadPool.dll"
          ],
          "compileAssemblies": [
            "lib/contract/System.Threading.ThreadPool.dll"
          ]
        }
      },
      "files": [
        "License.rtf",
        "System.Threading.ThreadPool.4.0.10-beta-22725.nupkg",
        "System.Threading.ThreadPool.4.0.10-beta-22725.nupkg.sha512",
        "System.Threading.ThreadPool.nuspec",
        "lib/aspnetcore50/System.Threading.ThreadPool.dll",
        "lib/contract/System.Threading.ThreadPool.dll",
        "lib/net45/System.Threading.ThreadPool.dll",
        "lib/portable-wpa81+wp80+win80+net45+aspnetcore50/System.Threading.ThreadPool.dll"
      ]
    },
    "System.Threading.Timer/4.0.0-beta-22725": {
      "serviceable": false,
      "sha": "Uc4UkuSMdejhy5oWy6ocg7D1Rqol5ImZ377NzKjIjbKJZsNzUZB3YneNd/iHqVhFJg6LokCPvBAIPWqSdvKTIw==",
      "frameworks": {
        "DNX,Version=v4.5.1": {
          "dependencies": {
            "System.Runtime": "4.0.0-beta-22725"
          },
          "frameworkAssemblies": [],
          "runtimeAssemblies": [
            "lib/net45/System.Threading.Timer.dll"
          ],
          "compileAssemblies": [
            "lib/net45/System.Threading.Timer.dll"
          ]
        },
        "DNXCore,Version=v5.0": {
          "dependencies": {
            "System.Runtime": "4.0.0-beta-22725"
          },
          "frameworkAssemblies": [],
          "runtimeAssemblies": [
            "lib/aspnetcore50/System.Threading.Timer.dll"
          ],
          "compileAssemblies": [
            "lib/contract/System.Threading.Timer.dll"
          ]
        }
      },
      "files": [
        "License.rtf",
        "System.Threading.Timer.4.0.0-beta-22725.nupkg",
        "System.Threading.Timer.4.0.0-beta-22725.nupkg.sha512",
        "System.Threading.Timer.nuspec",
        "lib/aspnetcore50/System.Threading.Timer.dll",
        "lib/contract/System.Threading.Timer.dll",
        "lib/net45/System.Threading.Timer.dll",
        "lib/portable-wpa81+wp80+win80+net45+aspnetcore50/System.Threading.Timer.dll"
      ]
    },
    "System.Xml.ReaderWriter/4.0.10-beta-22725": {
      "serviceable": false,
      "sha": "7hDshMospWwoMNqG2j0SyU9PJPKGCtSmdOLwWtIB9xaIkpA1qDyxhSjCH9Wuj3PtIehpAAmaurKYzf8b8QfojQ==",
      "frameworks": {
        "DNX,Version=v4.5.1": {
          "dependencies": {
            "System.IO": "4.0.0-beta-22725",
            "System.Runtime": "4.0.0-beta-22725",
            "System.Text.Encoding": "4.0.0-beta-22725",
            "System.Threading.Tasks": "4.0.0-beta-22725"
          },
          "frameworkAssemblies": [],
          "runtimeAssemblies": [
            "lib/net45/System.Xml.ReaderWriter.dll"
          ],
          "compileAssemblies": [
            "lib/net45/System.Xml.ReaderWriter.dll"
          ]
        },
        "DNXCore,Version=v5.0": {
          "dependencies": {
            "System.IO": "4.0.0-beta-22725",
            "System.Runtime": "4.0.0-beta-22725",
            "System.Text.Encoding": "4.0.0-beta-22725",
            "System.Threading.Tasks": "4.0.0-beta-22725"
          },
          "frameworkAssemblies": [],
          "runtimeAssemblies": [
            "lib/aspnetcore50/System.Xml.ReaderWriter.dll"
          ],
          "compileAssemblies": [
            "lib/contract/System.Xml.ReaderWriter.dll"
          ]
        }
      },
      "files": [
        "License.rtf",
        "System.Xml.ReaderWriter.4.0.10-beta-22725.nupkg",
        "System.Xml.ReaderWriter.4.0.10-beta-22725.nupkg.sha512",
        "System.Xml.ReaderWriter.nuspec",
        "lib/aspnetcore50/System.Xml.ReaderWriter.dll",
        "lib/contract/System.Xml.ReaderWriter.dll",
        "lib/net45/System.Xml.ReaderWriter.dll",
        "lib/portable-wpa81+wp80+win80+net45+aspnetcore50/System.Xml.ReaderWriter.dll"
      ]
    },
    "System.Xml.XDocument/4.0.10-beta-22725": {
      "serviceable": false,
      "sha": "X/bw1g5AU33J6BpiH+kXEsybqHaSI+RNZXQFhVa1eL6V9COMZxYkWaLVnw49T/X4uKdDCK0eu0APaWg/1uYXQA==",
      "frameworks": {
        "DNX,Version=v4.5.1": {
          "dependencies": {
            "System.IO": "4.0.0-beta-22725",
            "System.Runtime": "4.0.0-beta-22725",
            "System.Xml.ReaderWriter": "4.0.10-beta-22725"
          },
          "frameworkAssemblies": [],
          "runtimeAssemblies": [
            "lib/net45/System.Xml.XDocument.dll"
          ],
          "compileAssemblies": [
            "lib/net45/System.Xml.XDocument.dll"
          ]
        },
        "DNXCore,Version=v5.0": {
          "dependencies": {
            "System.IO": "4.0.0-beta-22725",
            "System.Runtime": "4.0.0-beta-22725",
            "System.Xml.ReaderWriter": "4.0.10-beta-22725"
          },
          "frameworkAssemblies": [],
          "runtimeAssemblies": [
            "lib/aspnetcore50/System.Xml.XDocument.dll"
          ],
          "compileAssemblies": [
            "lib/contract/System.Xml.XDocument.dll"
          ]
        }
      },
      "files": [
        "License.rtf",
        "System.Xml.XDocument.4.0.10-beta-22725.nupkg",
        "System.Xml.XDocument.4.0.10-beta-22725.nupkg.sha512",
        "System.Xml.XDocument.nuspec",
        "lib/aspnetcore50/System.Xml.XDocument.dll",
        "lib/contract/System.Xml.XDocument.dll",
        "lib/net45/System.Xml.XDocument.dll",
        "lib/portable-wpa81+wp80+win80+net45+aspnetcore50/System.Xml.XDocument.dll"
      ]
    },
    "System.Xml.XmlSerializer/4.0.10-beta-22725": {
      "serviceable": false,
      "sha": "FARIEBjHRfWgECQOTl9uCiP/v6Ndkt6ckqpoVCPJUef0+0MmHwKJ3NxolkH8deOcmkVKDtvieTyvk9ZPbeKdqg==",
      "frameworks": {
        "DNX,Version=v4.5.1": {
          "dependencies": {
            "System.IO": "4.0.0-beta-22725",
            "System.Runtime": "4.0.0-beta-22725",
            "System.Xml.ReaderWriter": "4.0.10-beta-22725"
          },
          "frameworkAssemblies": [],
          "runtimeAssemblies": [
            "lib/net45/System.Xml.XmlSerializer.dll"
          ],
          "compileAssemblies": [
            "lib/net45/System.Xml.XmlSerializer.dll"
          ]
        },
        "DNXCore,Version=v5.0": {
          "dependencies": {
            "System.IO": "4.0.0-beta-22725",
            "System.Runtime": "4.0.0-beta-22725",
            "System.Xml.ReaderWriter": "4.0.10-beta-22725"
          },
          "frameworkAssemblies": [],
          "runtimeAssemblies": [
            "lib/aspnetcore50/System.Xml.XmlSerializer.dll"
          ],
          "compileAssemblies": [
            "lib/contract/System.Xml.XmlSerializer.dll"
          ]
        }
      },
      "files": [
        "License.rtf",
        "System.Xml.XmlSerializer.4.0.10-beta-22725.nupkg",
        "System.Xml.XmlSerializer.4.0.10-beta-22725.nupkg.sha512",
        "System.Xml.XmlSerializer.nuspec",
        "lib/aspnetcore50/System.Xml.XmlSerializer.dll",
        "lib/contract/System.Xml.XmlSerializer.dll",
        "lib/net45/System.Xml.XmlSerializer.dll",
        "lib/portable-wpa81+wp80+win80+net45+aspnetcore50/System.Xml.XmlSerializer.dll"
      ]
    }
  }
}